Workbook

Sheet Tesla Formatting
A1: Color | B1: Description | C1: HEX
A2: Tesla Red | B2: Signature red accent | C2: #E82127
A3: Jet Black | B3: Deep black used in logo/typography | C3: #111111
A4: Steel Gray | B4: Medium gray | C4: #666666
A5: Light Gray / Silver | B5: Background or accent | C5: #E5E5E5
A6: White | B6: Clean base color | C6: #FFFFFF

Sheet Tesla Valuation
B1: Base year | C1: 1 | D1: 2 | E1: 3 | F1: 4 | G1: 5 | H1: 6 | I1: 7 | J1: 8 | K1: 9 | L1: 10 | M1: Terminal year
A2: Revenue growth rate | C2: ='Assumptions>>>'!B4 -> 0.086372907 | D2: ='Assumptions>>>'!C4 -> 0.078954897 | E2: ='Assumptions>>>'!D4 -> 0.07271537 | F2: ='Assumptions>>>'!E4 -> 0.067394942 | G2: ='Assumptions>>>'!F4 -> 0.062805018 | H2: ='Assumptions>>>'!G4 -> 0.058805216 | I2: ='Assumptions>>>'!H4 -> 0.055288897 | J2: ='Assumptions>>>'!I4 -> 0.052173618 | ... L2: ='Assumptions>>>'!K4 -> 0.04371547 | M2: 0.04
A3: Revenues | B3: ='Inputs From 10k'!B2 -> 97690 | C3: =B3*(1+C2) -> 106127.77 | D3: =C3*(1+D2) -> 114507.08 | E3: =D3*(1+E2) -> 122833.5 | F3: =E3*(1+F2) -> 131111.86 | G3: =F3*(1+G2) -> 139346.34 | H3: =G3*(1+H2) -> 147540.63 | I3: =H3*(1+I2) -> 155697.99 | J3: =I3*(1+J2) -> 163821.32 | ... M3: =L3*(1+M2) -> 186309.93
A4: EBIT (Operating) margin | B4: ='Inputs From 10k'!B3 -> 0.072433207 | C4: =B4*(1+0.001)^C1 -> 0.07250564 | D4: =C4*(1+0.001)^D1 -> 0.072650724 | E4: =D4*(1+0.001)^E1 -> 0.072868894 | F4: =E4*(1+0.001)^F1 -> 0.073160807 | G4: =F4*(1+0.001)^G1 -> 0.073527344 | H4: =G4*(1+0.001)^H1 -> 0.073969612 | I4: =H4*(1+0.001)^I1 -> 0.074488955 | J4: =I4*(1+0.001)^J1 -> 0.075086957 | ... L4: =K4*(1+0.001)^L1 -> 0.076526522 | M4: =L4*(1+0.001)^11 -> 0.077372535
A5: EBIT (Operating income) | B5: =B3*B4 -> 7076 | C5: =C3*C4 -> 7694.8619 | D5: =D3*D4 -> 8319.022 | E5: =E3*E4 -> 8950.7414 | F5: =F3*F4 -> 9592.2493 | G5: =G3*G4 -> 10245.766 | H5: =H3*H4 -> 10913.523 | I5: =I3*I4 -> 11597.781 | ... M5: =M3*M4 -> 14415.271
A6: Tax rate | B6: ='Inputs From 10k'!B4 -> 0.2 | C6: 0.25 | D6: 0.25 | E6: 0.25 | F6: 0.25 | G6: 0.25 | H6: 0.25 | I6: 0.25 | J6: 0.25 | K6: 0.25 | L6: 0.25 | M6: 0.25
A7: EBIT(1-t) | B7: =B5*(1-B6) -> 5660.8 | C7: =C5*(1-C6) -> 5771.1464 | D7: =D5*(1-D6) -> 6239.2665 | E7: =E5*(1-E6) -> 6713.056 | F7: =F5*(1-F6) -> 7194.187 | G7: =G5*(1-G6) -> 7684.3247 | H7: =H5*(1-H6) -> 8185.1425 | I7: =I5*(1-I6) -> 8698.3355 | ... M7: =M5*(1-M6) -> 10811.453
A8: Sales to capital ratio | C8: 3 | D8: 3 | E8: 3 | F8: 3 | G8: 3 | H8: 2 | I8: 2 | J8: 2 | K8: 2 | L8: 2
A9: - Reinvestment | C9: =(C3-B3)/C8 -> 2812.5898 | D9: =(D3-C3)/D8 -> 2793.1024 | E9: =(E3-D3)/E8 -> 2775.4748 | F9: =(F3-E3)/F8 -> 2759.4522 | G9: =(G3-F3)/G8 -> 2744.8275 | H9: =(H3-G3)/H8 -> 4097.1458 | I9: =(I3-H3)/I8 -> 4078.6794 | J9: =(J3-I3)/J8 -> 4061.6638 | ... L9: =(L3-K3)/L8 -> 3751.6791 | M9: =M2/0.15*M7 -> 2883.0543
A10: FCFF | C10: =C7-C9 -> 2958.5566 | D10: =D7-D9 -> 3446.1641 | E10: =E7-E9 -> 3937.5812 | F10: =F7-F9 -> 4434.7348 | G10: =G7-G9 -> 4939.4972 | H10: =H7-H9 -> 4087.9967 | I10: =I7-I9 -> 4619.6561 | J10: =J7-J9 -> 5163.9694 | ... M10: =M7-M9 -> 7928.3992
A12: Cost of capital | C12: 0.09 | D12: =C12-0.01/9 -> 0.088888889 | E12: =D12-0.01/9 -> 0.087777778 | F12: =E12-0.01/9 -> 0.086666667 | G12: =F12-0.01/9 -> 0.085555556 | H12: =G12-0.01/9 -> 0.084444444 | I12: =H12-0.01/9 -> 0.083333333 | J12: =I12-0.01/9 -> 0.082222222 | K12: =J12-0.01/9 -> 0.081111111 | L12: =K12-0.01/9 -> 0.08 | M12: 0.08
A13: Cumulated discount factor | C13: =1/(1+C12) -> 0.91743119 | D13: =C13*1/(1+D12) -> 0.84253885 | E13: =D13*1/(1+E12) -> 0.77455053 | F13: =E13*1/(1+F12) -> 0.71277656 | G13: =F13*1/(1+G12) -> 0.65660072 | H13: =G13*1/(1+H12) -> 0.60547197 | I13: =H13*1/(1+I12) -> 0.55889721 | J13: =I13*1/(1+J12) -> 0.51643479 | K13: =J13*1/(1+K12) -> 0.47768891 | L13: =K13*1/(1+L12) -> 0.44230455
A14: PV(FCFF) | C14: =C10*C13 -> 2714.2721 | D14: =D10*D13 -> 2903.5272 | E14: =E10*E13 -> 3049.8556 | F14: =F10*F13 -> 3160.975 | G14: =G10*G13 -> 3243.2774 | H14: =H10*H13 -> 2475.1674 | I14: =I10*I13 -> 2581.9129 | J14: =J10*J13 -> 2666.8535 | ... L14: =L10*L13 -> 2888.3727
A16: Terminal cash flow | B16: =M10 -> 7928.3992
A17: Terminal cost of capital | B17: 0.08 | F17: Color Key:
A18: Terminal value | B18: =B16/(B17-M2) -> 198209.98 | F18: Linked Cells | G18: Cells you need to fill manually (input assumptions or drivers).
A19: PV(Terminal value) | B19: =B18*L13 -> 87669.176 | F19: Hard Coded | G19: Pre-filled data that is fixed or used as a reference by other cells.
A20: PV (CF over next 10 years) | B20: =SUM(C14:L14) -> 28475.632 | F20: Formula | G20: Formula cells that will auto-populate based on linked inputs.
A21: Sum of PV | B21: =B20+B19 -> 116144.81
A22: Probability of failure = | B22: 0
A23: Proceeds if firm fails = | B23: =200000 -> 200000
A24: Value of operating assets = | B24: =B21*(1-B22)+B22*B23 -> 116144.81
A25: - Debt | B25: ='Inputs From 10k'!B5 -> 7907
A26: + Cash | B26: ='Inputs From 10k'!B6 -> 36563
A27: Value of equity | B27: =B24-B25+B26 -> 144800.81
A28: Number of shares | B28: 3200
A29: Estimated value /share | B29: =B27/B28 -> 45.250253

Sheet Inputs From 10k
A1: Input | B1: Value | C1: Place in the 10K | D1: Formula
A2: Total Revenue | B2: 97690 | C2: PG. 50, Revenue Recognition
A3: Operatin Margin | B3: =7076/97690 -> 0.072433207 | C3: 7,076 from pg. 52, Consolidated statement of operations | D3: Operating Income/Total Revenue
A4: Tax Rate | B4: 0.2 | C4: Effective Tax Rate
A5: Debt | B5: 7907
A6: Cash | B6: 36563

Sheet Assumptions>>>
A1: Year | B1: 1 | C1: =B1+1 -> 2 | D1: =C1+1 -> 3 | E1: =D1+1 -> 4 | F1: =E1+1 -> 5 | G1: =F1+1 -> 6 | H1: =G1+1 -> 7 | I1: =H1+1 -> 8 | J1: =I1+1 -> 9 | K1: =J1+1 -> 10
A2: Unadjusted Growth Rate (Based on Historicals) | B2: ='Unadjusted Growth Rate (Calc)'!H14 -> 0.085372907 | C2: ='Unadjusted Growth Rate (Calc)'!H15 -> 0.077954897 | D2: ='Unadjusted Growth Rate (Calc)'!H16 -> 0.07171537 | E2: ='Unadjusted Growth Rate (Calc)'!H17 -> 0.066394942 | F2: ='Unadjusted Growth Rate (Calc)'!H18 -> 0.061805018 | G2: ='Unadjusted Growth Rate (Calc)'!H19 -> 0.057805216 | H2: ='Unadjusted Growth Rate (Calc)'!H20 -> 0.054288897 | I2: ='Unadjusted Growth Rate (Calc)'!H21 -> 0.051173618 | J2: ='Unadjusted Growth Rate (Calc)'!H22 -> 0.04673178 | K2: ='Unadjusted Growth Rate (Calc)'!H23 -> 0.04271547
A3: Adjusted Growth Rate (Growth & Risk Factors)
A4: Most Likely Adjusted Growth Rate | B4: =B2+'Adjusted Growth Rate (G&R Calc)'!$D$29 -> 0.086372907 | C4: =C2+'Adjusted Growth Rate (G&R Calc)'!$D$29 -> 0.078954897 | D4: =D2+'Adjusted Growth Rate (G&R Calc)'!$D$29 -> 0.07271537 | E4: =E2+'Adjusted Growth Rate (G&R Calc)'!$D$29 -> 0.067394942 | F4: =F2+'Adjusted Growth Rate (G&R Calc)'!$D$29 -> 0.062805018 | G4: =G2+'Adjusted Growth Rate (G&R Calc)'!$D$29 -> 0.058805216 | H4: =H2+'Adjusted Growth Rate (G&R Calc)'!$D$29 -> 0.055288897 | I4: =I2+'Adjusted Growth Rate (G&R Calc)'!$D$29 -> 0.052173618 | ... K4: =K2+'Adjusted Growth Rate (G&R Calc)'!$D$29 -> 0.04371547
A5: Worst Case Growth Rate | B5: =B2+'Adjusted Growth Rate (G&R Calc)'!$D$28 -> -0.13462709 | C5: =C2+'Adjusted Growth Rate (G&R Calc)'!$D$28 -> -0.1420451 | D5: =D2+'Adjusted Growth Rate (G&R Calc)'!$D$28 -> -0.14828463 | E5: =E2+'Adjusted Growth Rate (G&R Calc)'!$D$28 -> -0.15360506 | F5: =F2+'Adjusted Growth Rate (G&R Calc)'!$D$28 -> -0.15819498 | G5: =G2+'Adjusted Growth Rate (G&R Calc)'!$D$28 -> -0.16219478 | H5: =H2+'Adjusted Growth Rate (G&R Calc)'!$D$28 -> -0.1657111 | I5: =I2+'Adjusted Growth Rate (G&R Calc)'!$D$28 -> -0.16882638 | ... K5: =K2+'Adjusted Growth Rate (G&R Calc)'!$D$28 -> -0.17728453
A6: Best Case Growth Rate | B6: =B2+'Adjusted Growth Rate (G&R Calc)'!$D$30 -> 0.16037291 | C6: =C2+'Adjusted Growth Rate (G&R Calc)'!$D$30 -> 0.1529549 | D6: =D2+'Adjusted Growth Rate (G&R Calc)'!$D$30 -> 0.14671537 | E6: =E2+'Adjusted Growth Rate (G&R Calc)'!$D$30 -> 0.14139494 | F6: =F2+'Adjusted Growth Rate (G&R Calc)'!$D$30 -> 0.13680502 | G6: =G2+'Adjusted Growth Rate (G&R Calc)'!$D$30 -> 0.13280522 | H6: =H2+'Adjusted Growth Rate (G&R Calc)'!$D$30 -> 0.1292889 | I6: =I2+'Adjusted Growth Rate (G&R Calc)'!$D$30 -> 0.12617362 | ... K6: =K2+'Adjusted Growth Rate (G&R Calc)'!$D$30 -> 0.11771547

Sheet Unadjusted Growth Rate (Calc)
A1: Year | B1: Index (X) | C1: Historical Revenue | D1: YOY Growth Rates
A2: 2014 | B2: 1 | C2: 3.2 | D2: N/A
A3: =A2+1 -> 2015 | B3: =B2+1 -> 2 | C3: 4 | D3: =1- (C2/C3) -> 0.2
A4: =A3+1 -> 2016 | B4: =B3+1 -> 3 | C4: 7 | D4: =1- (C3/C4) -> 0.42857143
A5: =A4+1 -> 2017 | B5: =B4+1 -> 4 | C5: 11.8 | D5: =1- (C4/C5) -> 0.40677966
A6: =A5+1 -> 2018 | B6: =B5+1 -> 5 | C6: 21.5 | D6: =1- (C5/C6) -> 0.45116279
A7: =A6+1 -> 2019 | B7: =B6+1 -> 6 | C7: 24.6 | D7: =1- (C6/C7) -> 0.12601626
A8: =A7+1 -> 2020 | B8: =B7+1 -> 7 | C8: 31.5 | D8: =1- (C7/C8) -> 0.21904762
A9: =A8+1 -> 2021 | B9: =B8+1 -> 8 | C9: 53.8 | D9: =1- (C8/C9) -> 0.41449814
A10: =A9+1 -> 2022 | B10: =B9+1 -> 9 | C10: 81.5 | D10: =1- (C9/C10) -> 0.3398773
A11: =A10+1 -> 2023 | B11: =B10+1 -> 10 | C11: 96.8 | D11: =1- (C10/C11) -> 0.15805785
A12: =A11+1 -> 2024 | B12: =B11+1 -> 11 | C12: 97.69 | D12: =1-(C11/C12) -> 0.0091104514
A13: Year | B13: Index (X) | D13: Linear Predicted Revenue ($B) | E13: Logarithmic Revenue ($B) | F13: Log Growth Rate | G13: Linear Growth Rate | H13: Weighted Average
A14: =A12+1 -> 2025 | B14: =B12+1 -> 12 | D14: =10.556*B14-23.936 -> 102.736 | E14: =40.583*LN(B14)-25.173 -> 75.671967 | F14: =1-(E14/E15) -> 0.041160152 | G14: =1-(D14/D15) -> 0.093175158 | H14: =0.15*F14+0.85*G14 -> 0.085372907
A15: =A14+1 -> 2026 | B15: =B14+1 -> 13 | D15: =10.556*B15-23.936 -> 113.292 | E15: =40.583*LN(B15)-25.173 -> 78.92034 | F15: =1-(E15/E16) -> 0.036709414 | G15: =1-(D15/D16) -> 0.085233512 | H15: =0.15*F15+0.85*G15 -> 0.077954897
A16: =A15+1 -> 2027 | B16: =B15+1 -> 14 | D16: =10.556*B16-23.936 -> 123.848 | E16: =40.583*LN(B16)-25.173 -> 81.927864 | F16: =1-(E16/E17) -> 0.033046269 | G16: =1-(D16/D17) -> 0.078539329 | H16: =0.15*F16+0.85*G16 -> 0.07171537
A17: =A16+1 -> 2028 | B17: =B16+1 -> 15 | D17: =10.556*B17-23.936 -> 134.404 | E17: =40.583*LN(B17)-25.173 -> 84.727801 | F17: =1-(E17/E18) -> 0.029985778 | G17: =1-(D17/D18) -> 0.072820088 | H17: =0.15*F17+0.85*G17 -> 0.066394942
A18: =A17+1 -> 2029 | B18: =B17+1 -> 16 | D18: =10.556*B18-23.936 -> 144.96 | E18: =40.583*LN(B18)-25.173 -> 87.346968 | F18: =1-(E18/E19) -> 0.027395647 | G18: =1-(D18/D19) -> 0.06787726 | H18: =0.15*F18+0.85*G18 -> 0.061805018
A19: =A18+1 -> 2030 | B19: =B18+1 -> 17 | D19: =10.556*B19-23.936 -> 155.516 | E19: =40.583*LN(B19)-25.173 -> 89.807297 | F19: =1-(E19/E20) -> 0.025178949 | G19: =1-(D19/D20) -> 0.063562792 | H19: =0.15*F19+0.85*G19 -> 0.057805216
A20: =A19+1 -> 2031 | B20: =B19+1 -> 18 | D20: =10.556*B20-23.936 -> 166.072 | E20: =40.583*LN(B20)-25.173 -> 92.126957 | F20: =1-(E20/E21) -> 0.023263177 | G20: =1-(D20/D21) -> 0.059764024 | H20: =0.15*F20+0.85*G20 -> 0.054288897
A21: =A20+1 -> 2032 | B21: =B20+1 -> 19 | D21: =10.556*B21-23.936 -> 176.628 | E21: =40.583*LN(B21)-25.173 -> 94.321167 | F21: =1-(E21/E22) -> 0.021593104 | G21: =1-(D21/D22) -> 0.056393709 | H21: =0.15*F21+0.85*G21 -> 0.051173618
A22: =A21+1 -> 2033 | B22: =B21+1 -> 20 | D22: =10.556*B22-23.936 -> 187.184 | E22: =40.583*LN(B22)-25.173 -> 96.402803 | F22: =1-(E22/E23) -> 0.020125979 | G22: =1-(D22/D23) -> 0.053383231 | H22: =0.2*F22+0.8*G22 -> 0.04673178
A23: =A22+1 -> 2034 | B23: =B22+1 -> 21 | D23: =10.556*B23-23.936 -> 197.74 | E23: =40.583*LN(B23)-25.173 -> 98.382854 | F23: =1-(E23/E24) -> 0.018828236 | G23: =1-(D23/D24) -> 0.050677881 | H23: =0.25*F23+0.75*G23 -> 0.04271547
A24: =A23+1 -> 2035 | B24: =B23+1 -> 22 | D24: =10.556*B24-23.936 -> 208.296 | E24: =40.583*LN(B24)-25.173 -> 100.27078 | F24: =1-(E24/E25) -> 0.017673182 | G24: =1-(D24/D25) -> 0.048233509 | H24: =0.3*F24+0.7*G24 -> 0.039065411
A25: =A24+1 -> 2036 | B25: =B24+1 -> 23 | D25: =10.556*B25-23.936 -> 218.852 | E25: =40.583*LN(B25)-25.173 -> 102.07476

Sheet Adjusted Growth Rate (G&R Calc)
A1: Mitigant strength | B1: Reduction | C1: Rationale
A2: Strong | B2: 60 – 70 % | C2: Vertical integration, multiple plants, clear execution history
A3: Moderate | B3: 40 – 50 % | C3: Some exposure remains but active management
A4: Weak | B4: 20 – 30 % | C4: Limited control or high external dependence
A6: Execution Strength | B6: Execution Likelihood (%) | C6: Rationale
A7: High | B7: 80–100% | C7: Strong operational track record, vertical integration, and proven ability to scale and deliver.
A8: Moderate | B8: 50–70% | C8: Solid execution capability but subject to timing, regulatory, or resource constraints.
A9: Low | B9: 20–40% | C9: Early-stage or uncertain initiatives with high dependence on external factors.
A11: Risk | B11: Mitigator | C11: Effect (before mitigation) | D11: OPEX Effect | E11: Mitigation strength | F11: Most-likely impact after mitigation | G11: Stong Mitigation (Assumes 65% for each)
A12: 1. Production & Factory Ramp | B12: Multi-plant redundancy (Austin, Berlin, Shanghai); automation upgrades. | C12: -0.05 | E12: 0.6 | F12: =C12*(1-E12) -> -0.02 | G12: =C12*(1-0.65) -> -0.0175
A13: 2. Battery & Raw-Material Supply | B13: Long-term contracts + in-house 4680 ramp. | C13: -0.04 | E13: 0.5 | F13: =C13*(1-E13) -> -0.02 | G13: =C13*(1-0.65) -> -0.014
A14: 3. Demand & Pricing Elasticity | B14: Financing / insurance integration; Model 2 broadens market. | C14: -0.06 | E14: 0.2 | F14: =C14*(1-E14) -> -0.048 | G14: =C14*(1-0.65) -> -0.021
A15: 4. Competitive Intensity & Product Cadence | B15: Brand loyalty; FSD software advantage; Supercharger ecosystem. | C15: -0.03 | E15: 0.5 | F15: =C15*(1-E15) -> -0.015 | G15: =C15*(1-0.65) -> -0.0105
A16: 5. Policy / Trade / FX | B16: Geographic diversification; local production; lobbying efforts. | C16: -0.04 | E16: 0.4 | F16: =C16*(1-E16) -> -0.024 | G16: =C16*(1-0.65) -> -0.014
D17: Total | E17: =SUM(F12:F16) -> -0.127 | F17: =SUM(G12:G16) -> -0.077
A19: Advantage | B19: Effect (before) | C19: OPEX Effect | D19: Execution likelihood | E19: Most-likely Execution | F19: Strong Execution (Assumes 80%)
A20: Energy & Storage Expansion | B20: 0.06 | D20: 0.8 | E20: =B20*D20 -> 0.048 | F20: =0.8*B20 -> 0.048
A21: FSD / Software Monetization | B21: 0.03 | D21: 0.6 | E21: =B21*D21 -> 0.018 | F21: =0.8*B21 -> 0.024
A22: Manufacturing Efficiency | B22: 0.03 | D22: 0.8 | E22: =B22*D22 -> 0.024 | F22: =0.8*B22 -> 0.024
A23: New Product Launches | B23: 0.04 | D23: 0.5 | E23: =B23*D23 -> 0.02 | F23: =0.8*B23 -> 0.032
A24: Geographic Expansion | B24: 0.03 | D24: 0.6 | E24: =B24*D24 -> 0.018 | F24: =0.8*B24 -> 0.024
D25: Total | E25: =SUM(E20:E24) -> 0.128 | F25: =SUM(F20:F24) -> 0.152
A27: Scenario | B27: Sum of risks | C27: Sum of advantages | D27: Net effect on growth
A28: Worst case | B28: =SUM(C12:C16) -> -0.22 | C28: 0 | D28: =B28+C28 -> -0.22
A29: Most likely (after mitigation/execution) | B29: =E17 -> -0.127 | C29: =E25 -> 0.128 | D29: =B29+C29 -> 0.001
A30: Optimistic (strong mitigation/execution) | B30: =F17 -> -0.077 | C30: =F25 -> 0.152 | D30: =B30+C30 -> 0.075

Sheet EBIT OP Margin (Calc)>

Sheet Cost of Sales Ratio (Calc)

Sheet OPEX Ratio (Calc)

Sheet Miscelanious Tabs>>>

Sheet Risks
A1: # | B1: Risk | C1: Mitigator | D1: Effect | E1: Result (% Change)
A2: =1 -> 1 | B2: Increase in new EV vehicles other than Tesla into the Market | D2: Decrease in market share | E2: -0.02
A3: =A2+1 -> 2 | B3: Delays in design and production(yearly) | D3: Decrease in market share
A4: =A3+1 -> 3 | B4: Reduction of tax credits and reduced subsidies | D4: Less affordable cars, revenue drops
A5: =A4+1 -> 4
A6: =A5+1 -> 5
A9: # | B9: Advantages | C9: Effect | D9: Result (% Change)
A10: 1
A11: =A10+1 -> 2
A12: =A11+1 -> 3
A13: =A12+1 -> 4
A14: =A13+1 -> 5

Sheet Sheet3

Sheet Valuation sheet (Original)
B1: Base year | C1: 1 | D1: 2 | E1: 3 | F1: 4 | G1: 5 | H1: 6 | I1: 7 | J1: 8 | K1: 9 | L1: 10 | M1: Terminal year
A2: Revenue growth rate | C2: ='Assumptions>>>'!B4 -> 0.086372907 | D2: ='Assumptions>>>'!C4 -> 0.078954897 | E2: ='Assumptions>>>'!D4 -> 0.07271537 | F2: ='Assumptions>>>'!E4 -> 0.067394942 | G2: ='Assumptions>>>'!F4 -> 0.062805018 | H2: ='Assumptions>>>'!G4 -> 0.058805216 | I2: ='Assumptions>>>'!H4 -> 0.055288897 | J2: ='Assumptions>>>'!I4 -> 0.052173618 | ... L2: ='Assumptions>>>'!K4 -> 0.04371547 | M2: 0.04
A3: Revenues | B3: ='Inputs From 10k'!B2 -> 97690 | C3: =B3*(1+C2) -> 106127.77 | D3: =C3*(1+D2) -> 114507.08 | E3: =D3*(1+E2) -> 122833.5 | F3: =E3*(1+F2) -> 131111.86 | G3: =F3*(1+G2) -> 139346.34 | H3: =G3*(1+H2) -> 147540.63 | I3: =H3*(1+I2) -> 155697.99 | J3: =I3*(1+J2) -> 163821.32 | ... M3: =L3*(1+M2) -> 186309.93
A4: EBIT (Operating) margin | B4: ='Inputs From 10k'!B3 -> 0.072433207 | C4: =B4*(1+0.001)^C1 -> 0.07250564 | D4: =C4*(1+0.001)^D1 -> 0.072650724 | E4: =D4*(1+0.001)^E1 -> 0.072868894 | F4: =E4*(1+0.001)^F1 -> 0.073160807 | G4: =F4*(1+0.001)^G1 -> 0.073527344 | H4: =G4*(1+0.001)^H1 -> 0.073969612 | I4: =H4*(1+0.001)^I1 -> 0.074488955 | J4: =I4*(1+0.001)^J1 -> 0.075086957 | ... L4: =K4*(1+0.001)^L1 -> 0.076526522 | M4: =L4*(1+0.001)^11 -> 0.077372535
A5: EBIT (Operating income) | B5: =B3*B4 -> 7076 | C5: =C3*C4 -> 7694.8619 | D5: =D3*D4 -> 8319.022 | E5: =E3*E4 -> 8950.7414 | F5: =F3*F4 -> 9592.2493 | G5: =G3*G4 -> 10245.766 | H5: =H3*H4 -> 10913.523 | I5: =I3*I4 -> 11597.781 | ... M5: =M3*M4 -> 14415.271
A6: Tax rate | B6: ='Inputs From 10k'!B4 -> 0.2 | C6: =B6*(1.01)^C1 -> 0.202 | D6: =C6*(1.01)^D1 -> 0.2060602 | E6: =D6*(1.01)^E1 -> 0.21230403 | F6: =E6*(1.01)^F1 -> 0.22092443 | G6: =F6*(1.01)^G1 -> 0.23219379 | H6: =G6*(1.01)^H1 -> 0.24647839 | I6: =H6*(1.01)^I1 -> 0.26425819 | J6: =I6*(1.01)^J1 -> 0.28615376 | ... L6: =K6*(1.01)^L1 -> 0.34570491 | M6: =L6*(1.01)^11 -> 0.38569203
A7: EBIT(1-t) | B7: =B5*(1-B6) -> 5660.8 | C7: =C5*(1-C6) -> 6140.4998 | D7: =D5*(1-D6) -> 6604.8027 | E7: =E5*(1-E6) -> 7050.4629 | F7: =F5*(1-F6) -> 7473.0872 | G7: =G5*(1-G6) -> 7866.7629 | H7: =H5*(1-H6) -> 8223.5757 | I7: =I5*(1-I6) -> 8532.9721 | ... M7: =M5*(1-M6) -> 8855.4161
A8: Sales to capital ratio | C8: 3 | D8: 3 | E8: 3 | F8: 3 | G8: 3 | H8: 2 | I8: 2 | J8: 2 | K8: 2 | L8: 2
A9: - Reinvestment | C9: =(C3-B3)/C8 -> 2812.5898 | D9: =(D3-C3)/D8 -> 2793.1024 | E9: =(E3-D3)/E8 -> 2775.4748 | F9: =(F3-E3)/F8 -> 2759.4522 | G9: =(G3-F3)/G8 -> 2744.8275 | H9: =(H3-G3)/H8 -> 4097.1458 | I9: =(I3-H3)/I8 -> 4078.6794 | J9: =(J3-I3)/J8 -> 4061.6638 | ... L9: =(L3-K3)/L8 -> 3751.6791 | M9: =M2/0.15*M7 -> 2361.4443
A10: FCFF | C10: =C7-C9 -> 3327.91 | D10: =D7-D9 -> 3811.7003 | E10: =E7-E9 -> 4274.9881 | F10: =F7-F9 -> 4713.635 | G10: =G7-G9 -> 5121.9354 | H10: =H7-H9 -> 4126.4299 | I10: =I7-I9 -> 4454.2927 | J10: =J7-J9 -> 4719.2477 | ... M10: =M7-M9 -> 6493.9718
A12: Cost of capital | C12: 0.09 | D12: =C12-0.01/9 -> 0.088888889 | E12: =D12-0.01/9 -> 0.087777778 | F12: =E12-0.01/9 -> 0.086666667 | G12: =F12-0.01/9 -> 0.085555556 | H12: =G12-0.01/9 -> 0.084444444 | I12: =H12-0.01/9 -> 0.083333333 | J12: =I12-0.01/9 -> 0.082222222 | K12: =J12-0.01/9 -> 0.081111111 | L12: =K12-0.01/9 -> 0.08 | M12: 0.08
A13: Cumulated discount factor | C13: =1/(1+C12) -> 0.91743119 | D13: =C13*1/(1+D12) -> 0.84253885 | E13: =D13*1/(1+E12) -> 0.77455053 | F13: =E13*1/(1+F12) -> 0.71277656 | G13: =F13*1/(1+G12) -> 0.65660072 | H13: =G13*1/(1+H12) -> 0.60547197 | I13: =H13*1/(1+I12) -> 0.55889721 | J13: =I13*1/(1+J12) -> 0.51643479 | K13: =J13*1/(1+K12) -> 0.47768891 | L13: =K13*1/(1+L12) -> 0.44230455
A14: PV(FCFF) | C14: =C10*C13 -> 3053.1284 | D14: =D10*D13 -> 3211.5056 | E14: =E10*E13 -> 3311.1943 | F14: =F10*F13 -> 3359.7685 | G14: =G10*G13 -> 3363.0665 | H14: =H10*H13 -> 2498.4377 | I14: =I10*I13 -> 2489.4918 | J14: =J10*J13 -> 2437.1837 | ... L14: =L10*L13 -> 2308.0491
A16: Terminal cash flow | B16: =M10 -> 6493.9718
A17: Terminal cost of capital | B17: 0.08 | F17: Color Key:
A18: Terminal value | B18: =B16/(B17-M2) -> 162349.29
A19: PV(Terminal value) | B19: =B18*L13 -> 71807.831 | G19: Cells you need to fill
A20: PV (CF over next 10 years) | B20: =SUM(C14:L14) -> 28432.118 | G20: Pre-filled cells with data that is used by other cells
A21: Sum of PV | B21: =B20+B19 -> 100239.95 | G21: Cells with formulas that will auto-fill once you input data in green cells
A22: Probability of failure = | B22: 0
A23: Proceeds if firm fails = | B23: =200000 -> 200000
A24: Value of operating assets = | B24: =B21*(1-B22)+B22*B23 -> 100239.95
A25: - Debt | B25: ='Inputs From 10k'!B5 -> 7907
A26: + Cash | B26: ='Inputs From 10k'!B6 -> 36563
A27: Value of equity | B27: =B24-B25+B26 -> 128895.95
A28: Number of shares | B28: 3200
A29: Estimated value /share | B29: =B27/B28 -> 40.279984
